odoo/addons/pos_product_template_configurator/README.rst
odoo/addons/pos_product_template_configurator/__init__.py
odoo/addons/pos_product_template_configurator/__manifest__.py
odoo/addons/pos_product_template_configurator/i18n/es.po
odoo/addons/pos_product_template_configurator/i18n/it.po
odoo/addons/pos_product_template_configurator/i18n/pos_product_template_configurator.pot
odoo/addons/pos_product_template_configurator/readme/CONFIGURE.rst
odoo/addons/pos_product_template_configurator/readme/CONTRIBUTORS.rst
odoo/addons/pos_product_template_configurator/readme/DESCRIPTION.rst
odoo/addons/pos_product_template_configurator/readme/ROADMAP.rst
odoo/addons/pos_product_template_configurator/static/description/icon.png
odoo/addons/pos_product_template_configurator/static/description/index.html
odoo/addons/pos_product_template_configurator/static/img/configurator.png
odoo/addons/pos_product_template_configurator/static/src/js/ProductConfiguratorPopup.js
odoo/addons/pos_product_template_configurator/static/src/js/SelectVariantPopup.js
odoo/addons/pos_product_template_configurator/static/src/js/models.js
odoo/addons/pos_product_template_configurator/static/src/js/ppt.js
odoo/addons/pos_product_template_configurator/static/src/xml/SelectVariantPopup.xml
odoo/addons/pos_product_template_configurator/views/assets.xml
odoo14_addon_pos_product_template_configurator-14.0.1.0.1.dev7.dist-info/METADATA
odoo14_addon_pos_product_template_configurator-14.0.1.0.1.dev7.dist-info/WHEEL
odoo14_addon_pos_product_template_configurator-14.0.1.0.1.dev7.dist-info/top_level.txt
odoo14_addon_pos_product_template_configurator-14.0.1.0.1.dev7.dist-info/RECORD
