Metadata-Version: 2.1
Name: odoo14-addon-pos_product_template_configurator
Version: 14.0.1.0.1.dev7
Summary: Manage Product Template in Front End Point Of Sale via Configurator
Home-page: https://github.com/OCA/pos
Author: Ooops, Cetmix, Odoo Community Association (OCA)
Author-email: support@odoo-community.org
License: AGPL-3
Classifier: Programming Language :: Python
Classifier: Framework :: Odoo
Classifier: Framework :: Odoo :: 14.0
Classifier: License :: OSI Approved :: GNU Affero General Public License v3
Requires-Python: >=3.6
Requires-Dist: odoo14-addon-pos-product-template
Requires-Dist: odoo<14.1dev,>=14.0a
